{
  "version": "1.0",
  "description": "Proaktive Systemoptimierung basierend auf Metadaten und Event-Mustern",
  "improvements": [
    {
      "id": "IMP_POWER_PLAN",
      "name": "Energieplan nicht optimal",
      "category": "Performance",
      "severity": "warning",
      "description": "Das System verwendet einen Energiesparplan statt Höchstleistung. Auf Workstations und Servern kann das die Performance deutlich reduzieren – besonders bei kurzen CPU-Spitzen.",
      "check": "powerPlan",
      "checkValues": [
        "balanced",
        "power saver",
        "ausbalanciert",
        "energiesparmodus"
      ],
      "recommendations": [
        {
          "text": "Energieplan auf Höchstleistung setzen",
          "cmd": "powercfg /setactive 8c5e7fda-e8bf-4a96-9a85-a6e23a8c635c",
          "type": "fix",
          "risk": "low"
        },
        {
          "text": "Aktuellen Energieplan anzeigen",
          "cmd": "powercfg /getactivescheme",
          "type": "diagnose",
          "risk": "low"
        },
        {
          "text": "Alle verfügbaren Energiepläne anzeigen",
          "cmd": "powercfg /list",
          "type": "diagnose",
          "risk": "low"
        },
        {
          "text": "Set-PowerPlan-Win11 Script verwenden (setzt Höchstleistung + optimiert WLAN-Adapter)",
          "link": "powershell/Set-PowerPlan-Win11.ps1",
          "type": "maintenance",
          "risk": "medium"
        }
      ]
    },
    {
      "id": "IMP_UPTIME_HIGH",
      "name": "Langer Uptime – kein Neustart seit über 30 Tagen",
      "category": "Wartung",
      "severity": "info",
      "description": "Das System wurde seit mehr als 30 Tagen nicht neu gestartet. Windows Update Patches werden erst nach einem Neustart vollständig aktiv. Treiber und Dienste können sich in diesem Zustand instabil verhalten.",
      "check": "uptimeHours",
      "checkThreshold": 720,
      "recommendations": [
        {
          "text": "Letzten Boot-Zeitpunkt prüfen",
          "cmd": "(Get-Date) - (gcim Win32_OperatingSystem).LastBootUpTime",
          "type": "diagnose",
          "risk": "low"
        },
        {
          "text": "Neustart für Wartungsfenster einplanen",
          "cmd": "$action = New-ScheduledTaskAction -Execute 'shutdown.exe' -Argument '/r /f /t 0'\n$trigger = New-ScheduledTaskTrigger -Once -At '{time}'\nRegister-ScheduledTask -TaskName 'Wartungs-Neustart' -Action $action -Trigger $trigger -RunLevel Highest -User 'SYSTEM'",
          "type": "maintenance",
          "risk": "high"
        }
      ]
    },
    {
      "id": "IMP_DISK_SPACE_LOW",
      "name": "Wenig freier Speicherplatz",
      "category": "Hardware",
      "severity": "warning",
      "description": "Ein Laufwerk hat weniger als 15% freien Speicherplatz. Windows benötigt freien Speicher für Updates, temporäre Dateien, Swap und Sicherungspunkte. Unter 10% können Fehler auftreten.",
      "check": "diskFreePercent",
      "checkThreshold": 15,
      "recommendations": [
        {
          "text": "Datenträgerspeicher analysieren",
          "cmd": "Get-PSDrive -PSProvider FileSystem | Select Name, @{n='Free_GB';e={[math]::Round($_.Free/1GB,1)}}, @{n='Used_GB';e={[math]::Round($_.Used/1GB,1)}} | Sort Free_GB",
          "type": "diagnose",
          "risk": "low"
        },
        {
          "text": "Temporäre Dateien bereinigen",
          "cmd": "Remove-Item -Path $env:TEMP\\* -Recurse -Force -ErrorAction SilentlyContinue\nRemove-Item -Path C:\\Windows\\Temp\\* -Recurse -Force -ErrorAction SilentlyContinue",
          "type": "maintenance",
          "risk": "low"
        },
        {
          "text": "Windows-Komponentenspeicher bereinigen",
          "cmd": "DISM /Online /Cleanup-Image /StartComponentCleanup /ResetBase",
          "type": "maintenance",
          "risk": "high"
        }
      ]
    },
    {
      "id": "IMP_RAM_HIGH",
      "name": "Hohe RAM-Auslastung",
      "category": "Performance",
      "severity": "warning",
      "description": "Das System nutzt mehr als 85% des verfügbaren Arbeitsspeichers. Dies kann zu Leistungseinbrüchen führen und Windows veranlassen, Prozesse auszulagern.",
      "check": "ramUsedPercent",
      "checkThreshold": 85,
      "recommendations": [
        {
          "text": "Top RAM-Verbraucher anzeigen",
          "cmd": "Get-Process | Sort-Object WorkingSet64 -Descending | Select -First 10 Name, @{n='RAM_MB';e={[math]::Round($_.WorkingSet64/1MB,0)}}",
          "type": "diagnose",
          "risk": "low"
        },
        {
          "text": "Commit-Größe prüfen",
          "cmd": "Get-WmiObject Win32_OperatingSystem | Select @{n='Total_GB';e={[math]::Round($_.TotalVisibleMemorySize/1MB,1)}}, @{n='Free_GB';e={[math]::Round($_.FreePhysicalMemory/1MB,1)}}",
          "type": "diagnose",
          "risk": "low"
        }
      ]
    },
    {
      "id": "IMP_WINDOWS_VERSION",
      "name": "Windows-Version veraltet",
      "category": "Sicherheit",
      "severity": "warning",
      "description": "Das System läuft auf einer älteren Windows-Version. Ältere Versionen erhalten keine Sicherheitsupdates mehr und sind ein Sicherheitsrisiko.",
      "check": "windowsBuild",
      "checkMaxBuild": 19044,
      "recommendations": [
        {
          "text": "Aktuelle Windows-Version prüfen",
          "cmd": "Get-ComputerInfo | Select WindowsProductName, WindowsVersion, OsBuildNumber",
          "type": "diagnose",
          "risk": "low"
        },
        {
          "text": "Windows Update starten",
          "cmd": "Start-Process ms-settings:windowsupdate",
          "type": "fix",
          "risk": "low"
        }
      ]
    },
    {
      "id": "IMP_MANY_ERRORS",
      "name": "Überdurchschnittlich viele Fehler",
      "category": "System",
      "severity": "warning",
      "description": "Das System hat im analysierten Zeitraum ungewöhnlich viele Fehler-Ereignisse. Das deutet auf ein zugrunde liegendes Problem hin das noch nicht erkannt wurde.",
      "check": "errorCount",
      "checkThreshold": 50,
      "recommendations": [
        {
          "text": "Häufigste Fehlerquellen anzeigen",
          "cmd": "Get-WinEvent -FilterHashtable @{LogName='System','Application'; Level=1,2; StartTime=(Get-Date).AddDays(-7)} | Group-Object ProviderName | Sort Count -Desc | Select -First 10 Count, Name",
          "type": "diagnose",
          "risk": "low"
        },
        {
          "text": "Systemdateien prüfen",
          "cmd": "sfc /scannow",
          "type": "fix",
          "risk": "medium"
        }
      ]
    },
    {
      "id": "IMP_DEFENDER_DISABLED",
      "name": "Windows Defender Echtzeit-Schutz deaktiviert",
      "category": "Sicherheit",
      "severity": "warning",
      "description": "Der Echtzeit-Schutz von Windows Defender ist deaktiviert. Das System ist ohne aktiven Virenschutz. Klassischer MSP-Fall: Benutzer oder Software hat den Schutz abgeschaltet.",
      "check": "defenderDisabled",
      "recommendations": [
        {
          "text": "Defender-Status prüfen",
          "cmd": "Get-MpComputerStatus | Select RealTimeProtectionEnabled, AntivirusEnabled, AMServiceEnabled",
          "type": "diagnose",
          "risk": "low"
        },
        {
          "text": "Echtzeit-Schutz wieder aktivieren",
          "cmd": "Set-MpPreference -DisableRealtimeMonitoring $false",
          "type": "fix",
          "risk": "low"
        },
        {
          "text": "Defender-Ereignisse prüfen",
          "cmd": "Get-WinEvent -FilterHashtable @{LogName='Microsoft-Windows-Windows Defender/Operational'; Level=1,2,3} -MaxEvents 20 | Select TimeCreated, Message",
          "type": "diagnose",
          "risk": "low"
        }
      ]
    },
    {
      "id": "IMP_BITLOCKER_OFF",
      "name": "BitLocker nicht aktiv",
      "category": "Sicherheit",
      "severity": "info",
      "description": "Das Systemlaufwerk ist nicht mit BitLocker verschlüsselt. Bei Diebstahl oder Verlust des Geräts sind alle Daten ungeschützt lesbar. Besonders relevant für mobile Geräte und Laptops.",
      "check": "bitlockerOff",
      "recommendations": [
        {
          "text": "BitLocker-Status aller Laufwerke prüfen",
          "cmd": "Get-BitLockerVolume | Select MountPoint, ProtectionStatus, EncryptionMethod, VolumeStatus",
          "type": "diagnose",
          "risk": "low"
        },
        {
          "text": "BitLocker aktivieren (interaktiv)",
          "cmd": "manage-bde -on C: -RecoveryPassword",
          "type": "fix",
          "risk": "medium"
        },
        {
          "text": "Recovery Key sichern",
          "cmd": "manage-bde -protectors -get C:",
          "type": "maintenance",
          "risk": "low"
        }
      ]
    },
    {
      "id": "IMP_MANY_APPCRASH",
      "name": "Viele Anwendungsabstürze",
      "category": "Stabilität",
      "severity": "warning",
      "description": "Überdurchschnittlich viele Application Error Events (ID 1000) im Analysezeitraum. Das deutet auf instabile Software, fehlende Abhängigkeiten oder beschädigte Systemdateien hin.",
      "check": "appCrashCount",
      "checkThreshold": 5,
      "recommendations": [
        {
          "text": "Häufig abstürzende Anwendungen identifizieren",
          "cmd": "Get-WinEvent -FilterHashtable @{LogName='Application'; Id=1000} | Group-Object {$_.Properties[0].Value} | Sort Count -Desc | Select -First 10 Count, Name",
          "type": "diagnose",
          "risk": "low"
        },
        {
          "text": "Systemdateien auf Beschädigungen prüfen",
          "cmd": "sfc /scannow",
          "type": "fix",
          "risk": "medium"
        },
        {
          "text": ".NET Framework Versionen prüfen",
          "cmd": "Get-ChildItem 'HKLM:\\SOFTWARE\\Microsoft\\NET Framework Setup\\NDP' -Recurse | Get-ItemProperty -Name Version -EA 0 | Sort Version -Desc | Select PSChildName, Version",
          "type": "diagnose",
          "risk": "low"
        }
      ]
    },
    {
      "id": "IMP_MANY_AUTOSTARTS",
      "name": "Viele Autostart-Einträge",
      "category": "Performance",
      "severity": "info",
      "description": "Das System hat viele Autostart-Programme. Das verlängert die Boot-Zeit und belastet RAM und CPU dauerhaft. Klassischer Fall für Kundengeräte die über Jahre gewachsen sind.",
      "check": "autostartCount",
      "checkThreshold": 20,
      "recommendations": [
        {
          "text": "Autostart-Einträge anzeigen",
          "cmd": "Get-CimInstance Win32_StartupCommand | Select Name, Command, Location, User | Sort Name",
          "type": "diagnose",
          "risk": "low"
        },
        {
          "text": "Autostart-Verwaltung öffnen",
          "cmd": "msconfig",
          "type": "diagnose",
          "risk": "low"
        },
        {
          "text": "Startup-Impact im Task-Manager prüfen (Aufgaben-Manager → Start-Apps)",
          "cmd": "taskmgr",
          "type": "diagnose",
          "risk": "low"
        }
      ]
    },
    {
      "id": "IMP_BIOS_OLD",
      "name": "BIOS/Firmware möglicherweise veraltet",
      "category": "Hardware",
      "severity": "info",
      "description": "Das BIOS/UEFI-Datum ist mehr als 2 Jahre alt. Veraltete Firmware kann Sicherheitslücken enthalten oder Kompatibilitätsprobleme mit neuerer Hardware und Windows-Features verursachen.",
      "check": "biosAgeYears",
      "checkThreshold": 2,
      "recommendations": [
        {
          "text": "BIOS-Version und Datum anzeigen",
          "cmd": "Get-WmiObject -Class Win32_BIOS | Select Manufacturer, Name, Version, ReleaseDate",
          "type": "diagnose",
          "risk": "low"
        },
        {
          "text": "System-Hersteller und Modell prüfen (für Firmware-Update)",
          "cmd": "Get-WmiObject -Class Win32_ComputerSystem | Select Manufacturer, Model, SystemType",
          "type": "diagnose",
          "risk": "low"
        }
      ]
    },
    {
      "id": "IMP_WIN11_LOW_RAM",
      "name": "RAM für produktiven Alltag knapp",
      "category": "Performance",
      "severity": "info",
      "description": "Das System hat weniger als 12 GB RAM. Die Windows 11 Mindestanforderung (4 GB) wird zwar erfüllt, für den produktiven Support-Alltag mit Teams, Browser, Office und AV/EDR-Software sind 8 GB jedoch knapp. Empfehlung: mindestens 16 GB RAM für flüssiges Arbeiten.",
      "check": "ramBelowRecommended",
      "checkThreshold": 12,
      "recommendations": [
        {
          "text": "Aktuelle RAM-Verbraucher anzeigen",
          "cmd": "Get-Process | Sort-Object WorkingSet64 -Descending | Select -First 10 Name, @{n='RAM_MB';e={[math]::Round($_.WorkingSet64/1MB,0)}}",
          "type": "diagnose",
          "risk": "low"
        },
        {
          "text": "Verfügbaren und genutzten Speicher prüfen",
          "cmd": "Get-WmiObject Win32_OperatingSystem | Select @{n='Total_GB';e={[math]::Round($_.TotalVisibleMemorySize/1MB,1)}}, @{n='Free_GB';e={[math]::Round($_.FreePhysicalMemory/1MB,1)}}",
          "type": "diagnose",
          "risk": "low"
        },
        {
          "text": "Aufrüstung auf 16 GB RAM empfehlen",
          "type": "maintenance",
          "risk": "low"
        }
      ]
    }
  ]
}